.dir-locals.el
.djlintrc
.editorconfig
.envrc
.gitignore
.readthedocs.yaml
.woodpecker.yaml
AUTHORS
ChangeLog.rst
LICENSE
MANIFEST.in
Makefile
README.rst
manage.py
package-lock.json
package.json
pyproject.toml
pytest.ini
setup.cfg
setup.py
shell.nix
tox.ini
.gitea/pull_request_template.md
.github/FUNDING.yml
.github/SECURITY.md
.github/dependabot.yml
.github/pull_request_template.md
.github/ISSUE_TEMPLATE/issue.md
.github/workflows/ci.yml
allauth/__init__.py
allauth/app_settings.py
allauth/conftest.py
allauth/decorators.py
allauth/exceptions.py
allauth/models.py
allauth/ratelimit.py
allauth/urls.py
allauth/utils.py
allauth/account/__init__.py
allauth/account/adapter.py
allauth/account/admin.py
allauth/account/app_settings.py
allauth/account/apps.py
allauth/account/auth_backends.py
allauth/account/authentication.py
allauth/account/checks.py
allauth/account/decorators.py
allauth/account/fields.py
allauth/account/forms.py
allauth/account/managers.py
allauth/account/middleware.py
allauth/account/mixins.py
allauth/account/models.py
allauth/account/reauthentication.py
allauth/account/signals.py
allauth/account/stages.py
allauth/account/urls.py
allauth/account/utils.py
allauth/account/views.py
allauth/account/internal/__init__.py
allauth/account/internal/decorators.py
allauth/account/internal/stagekit.py
allauth/account/internal/textkit.py
allauth/account/internal/userkit.py
allauth/account/internal/flows/__init__.py
allauth/account/internal/flows/code_verification.py
allauth/account/internal/flows/email_verification.py
allauth/account/internal/flows/email_verification_by_code.py
allauth/account/internal/flows/login.py
allauth/account/internal/flows/login_by_code.py
allauth/account/internal/flows/logout.py
allauth/account/internal/flows/manage_email.py
allauth/account/internal/flows/password_change.py
allauth/account/internal/flows/password_reset.py
allauth/account/internal/flows/password_reset_by_code.py
allauth/account/internal/flows/phone_verification.py
django_allauth.egg-info/PKG-INFO
django_allauth.egg-info/SOURCES.txt
django_allauth.egg-info/dependency_links.txt
django_allauth.egg-info/not-zip-safe
django_allauth.egg-info/requires.txt
django_allauth.egg-info/top_level.txt
