Metadata-Version: 2.1
Name: django-allauth
Version: 65.8.0
Summary: Integrated set of Django applications addressing authentication, registration, account management as well as 3rd party (social) account authentication.
Home-page: https://allauth.org
Author: Raymond Penners
Author-email: raymond.penners@intenct.nl
License: MIT
Project-URL: Documentation, https://docs.allauth.org/en/latest/
Project-URL: Changelog, https://codeberg.org/allauth/django-allauth/src/branch/main/ChangeLog.rst
Project-URL: Source, https://codeberg.org/allauth/django-allauth
Project-URL: Tracker, https://codeberg.org/allauth/django-allauth/issues
Project-URL: Donate, https://github.com/sponsors/pennersr
Classifier: Development Status :: 5 - Production/Stable
Classifier: Intended Audience :: Developers
Classifier: Topic :: Software Development :: Libraries :: Python Modules
Classifier: Environment :: Web Environment
Classifier: Topic :: Internet
Classifier: License :: OSI Approved :: MIT License
Classifier: Operating System :: OS Independent
Classifier: Programming Language :: Python
Classifier: Programming Language :: Python :: 3
Classifier: Programming Language :: Python :: 3.8
Classifier: Programming Language :: Python :: 3.9
Classifier: Programming Language :: Python :: 3.10
Classifier: Programming Language :: Python :: 3.11
Classifier: Programming Language :: Python :: 3.12
Classifier: Programming Language :: Python :: 3.13
Classifier: Framework :: Django
Classifier: Framework :: Django :: 4.2
Classifier: Framework :: Django :: 5.0
Classifier: Framework :: Django :: 5.1
Classifier: Framework :: Django :: 5.2
Requires-Python: >=3.8
License-File: LICENSE
License-File: AUTHORS
Requires-Dist: Django>=4.2.16
Requires-Dist: asgiref>=3.8.1
Provides-Extra: mfa
Requires-Dist: qrcode>=7.0.0; extra == "mfa"
Requires-Dist: fido2>=1.1.2; extra == "mfa"
Provides-Extra: openid
Requires-Dist: python3-openid>=3.0.8; extra == "openid"
Provides-Extra: saml
Requires-Dist: python3-saml<2.0.0,>=1.15.0; extra == "saml"
Provides-Extra: steam
Requires-Dist: python3-openid>=3.0.8; extra == "steam"
Provides-Extra: socialaccount
Requires-Dist: requests-oauthlib>=0.3.0; extra == "socialaccount"
Requires-Dist: requests>=2.0.0; extra == "socialaccount"
Requires-Dist: pyjwt[crypto]>=1.7; extra == "socialaccount"
